test_package_bikarnap/__init__.py
test_package_bikarnap/module1.py
test_package_bikarnap/module2.py
test_package_bikarnap-0.3.dist-info/LICENSE
test_package_bikarnap-0.3.dist-info/METADATA
test_package_bikarnap-0.3.dist-info/WHEEL
test_package_bikarnap-0.3.dist-info/top_level.txt
test_package_bikarnap-0.3.dist-info/RECORD
